piefuzz/__init__.py
piefuzz/piefuzz.py
piefuzz-1.0.4.dist-info/DESCRIPTION.rst
piefuzz-1.0.4.dist-info/LICENSE.txt
piefuzz-1.0.4.dist-info/METADATA
piefuzz-1.0.4.dist-info/RECORD
piefuzz-1.0.4.dist-info/WHEEL
piefuzz-1.0.4.dist-info/metadata.json
piefuzz-1.0.4.dist-info/top_level.txt
