Metadata-Version: 2.0
Name: piefuzz
Version: 1.0.4
Summary: Pie wrapper for junegunn's fuzzyfinder (fzf)
Home-page: https://github.com/timeyyy/piefuzz
Author: timothy c eiechler
Author-email: timeyyy_da_man@hotmail.com
License: MIT
Keywords: pyfzf fzf fuzzyfinder fuzz find ctrl-p command-t
Platform: UNKNOWN
Classifier: Development Status :: 4 - Beta
Classifier: Intended Audience :: Developers
Classifier: License :: OSI Approved :: MIT License
Classifier: Operating System :: OS Independent
Classifier: Programming Language :: Python
Classifier: Topic :: Terminals
Classifier: Programming Language :: Python :: 3.4
Classifier: Programming Language :: Python :: 3.5
Requires-Dist: plumbum
